radiant/wrapper/__init__.py
radiant/wrapper/django_server.py
radiant/wrapper/html_server.py
radiant/wrapper/android/__init__.py
radiant/wrapper/android/permissions.py
radiant/wrapper/scripts/__init__.py
radiant/wrapper/scripts/radiant_p4a.py
radiant_wrapper-0.1a10.dist-info/licenses/LICENSE
radiant_wrapper-0.1a10.dist-info/METADATA
radiant_wrapper-0.1a10.dist-info/WHEEL
radiant_wrapper-0.1a10.dist-info/entry_points.txt
radiant_wrapper-0.1a10.dist-info/top_level.txt
radiant_wrapper-0.1a10.dist-info/RECORD
